utilsdsp/__init__.py
utilsdsp/utilsdsp_compress.py
utilsdsp/utilsdsp_dict.py
utilsdsp/utilsdsp_dirs.py
utilsdsp/utilsdsp_downloads.py
utilsdsp/utilsdsp_files.py
utilsdsp/utilsdsp_list.py
utilsdsp/utilsdsp_organizedirs.py
utilsdsp/utilsdsp_others.py
utilsdsp/utilsdsp_paths.py
utilsdsp/utilsdsp_sanitize.py
utilsdsp/utilsdsp_sizefile.py
utilsdsp-0.1.5.dist-info/LICENSE
utilsdsp-0.1.5.dist-info/METADATA
utilsdsp-0.1.5.dist-info/WHEEL
utilsdsp-0.1.5.dist-info/top_level.txt
utilsdsp-0.1.5.dist-info/RECORD
