Metadata-Version: 2.1
Name: utilsdsp
Version: 0.1.5
Summary: Algunas funciones útiles
Home-page: https://github.com/dunieskysp/utils_dsp
Author: Duniesky Salazar Pérez
Author-email: <duniesky.salazar@gmail.com>
Keywords: python,utilsdsp
Classifier: Development Status :: 3 - Alpha
Classifier: Programming Language :: Python :: 3
Classifier: Operating System :: MacOS :: MacOS X
Classifier: Operating System :: Microsoft :: Windows
License-File: LICENSE
Requires-Dist: outputstyles >=1.0.0
Requires-Dist: validators >=0.28.1
Requires-Dist: requests >=2.31.0
Requires-Dist: tqdm >=4.66.2
Requires-Dist: curl-cffi >=0.9.0
